[
  {
    "title": "城市轨交早高峰试点更高频发车",
    "summary": "本地交通部门宣布，三条通勤客流集中的轨交线路将在工作日早高峰试点更高频发车，目标是缩短站台等待时间并缓解换乘拥堵。",
    "content": "本地交通部门宣布，三条通勤客流集中的轨交线路将在工作日早高峰试点更高频发车，目标是缩短站台等待时间并缓解换乘拥堵。试点期内，运营方会持续观察客流、满载率和换乘站压力，并根据数据调整班次。",
    "url": "https://news.example.local/transit-frequency",
    "published": "2026-07-01T06:30:00+08:00",
    "source": "城市交通简报"
  },
  {
    "title": "多家银行下调部分消费贷利率",
    "summary": "多家银行更新消费贷产品页面，部分短期消费贷利率较上月有所下调，但申请条件和实际审批利率仍取决于个人资质。",
    "content": "多家银行更新消费贷产品页面，部分短期消费贷利率较上月有所下调，但申请条件和实际审批利率仍取决于个人资质。业内人士提醒，低利率不等于低成本，借款人仍需要关注期限、提前还款规则和综合费用。",
    "url": "https://news.example.local/consumer-loan-rate",
    "published": "2026-07-01T07:10:00+08:00",
    "source": "财经早知道"
  },
  {
    "title": "暑期出行平台增加亲子路线供给",
    "summary": "暑期出行需求升温，多家平台增加亲子游、研学游和短途周边游产品，同时提醒用户关注退改规则和天气变化。",
    "content": "暑期出行需求升温，多家平台增加亲子游、研学游和短途周边游产品，同时提醒用户关注退改规则和天气变化。平台数据显示，周末两天一夜产品预订增长明显，家庭用户更关注交通便利和安全保障。",
    "url": "https://news.example.local/summer-family-travel",
    "published": "2026-07-01T07:40:00+08:00",
    "source": "生活服务观察"
  },
  {
    "title": "国产大模型工具推出离线知识库模式",
    "summary": "一款国产大模型效率工具发布离线知识库模式，支持用户在本地索引文档并生成摘要，官方称默认不上传原文内容。",
    "content": "一款国产大模型效率工具发布离线知识库模式，支持用户在本地索引文档并生成摘要，官方称默认不上传原文内容。新功能面向个人知识管理和企业内部资料整理，但复杂检索和多端同步仍需后续版本完善。",
    "url": "https://news.example.local/local-knowledge-mode",
    "published": "2026-07-01T08:05:00+08:00",
    "source": "科技产品日报"
  },
  {
    "title": "社区医院延长工作日门诊时间",
    "summary": "部分社区医院宣布延长工作日傍晚门诊时间，方便上班族进行复诊、开药和基础检查。",
    "content": "部分社区医院宣布延长工作日傍晚门诊时间，方便上班族进行复诊、开药和基础检查。卫健部门表示，延时门诊先在需求较高的社区试点，后续会根据接诊量和医护排班评估是否扩大范围。",
    "url": "https://news.example.local/community-clinic-hours",
    "published": "2026-07-01T08:20:00+08:00",
    "source": "民生新闻"
  },
  {
    "title": "多地发布高温通勤保障提示",
    "summary": "多地气象部门发布高温提醒，建议户外通勤人群错峰出行，并关注地铁、公交站点的临时补水和降温服务。",
    "content": "多地气象部门发布高温提醒，建议户外通勤人群错峰出行，并关注地铁、公交站点的临时补水和降温服务。应急部门提示，连续高温会增加交通拥堵、用电负荷和户外作业风险，相关单位需同步调整排班和保障方案。",
    "url": "https://news.example.local/heat-commute-advisory",
    "published": "2026-07-01T08:35:00+08:00",
    "source": "城市服务台"
  },
  {
    "title": "本地商圈早餐店推出错峰优惠",
    "summary": "多个通勤商圈的早餐店推出错峰优惠，鼓励消费者避开 8 点前后的集中排队时段。",
    "content": "多个通勤商圈的早餐店推出错峰优惠，鼓励消费者避开 8 点前后的集中排队时段。商户表示，错峰折扣可以平滑早高峰订单压力，也让外卖骑手和门店备餐更稳定。",
    "url": "https://news.example.local/breakfast-offpeak",
    "published": "2026-07-01T08:45:00+08:00",
    "source": "消费观察"
  },
  {
    "title": "新能源车企公布城区辅助驾驶更新",
    "summary": "一家新能源车企公布城区辅助驾驶功能更新，新增复杂路口提醒和施工区域减速策略。",
    "content": "一家新能源车企公布城区辅助驾驶功能更新，新增复杂路口提醒和施工区域减速策略。公司称，新版本会先向部分车型灰度推送，驾驶员仍需保持接管准备，不能把辅助驾驶视为自动驾驶。",
    "url": "https://news.example.local/ev-urban-assist-update",
    "published": "2026-07-01T09:00:00+08:00",
    "source": "汽车科技简报"
  },
  {
    "title": "多家平台上线个人信息授权清单",
    "summary": "多家生活服务平台在设置页上线个人信息授权清单，用户可以集中查看定位、通讯录和相册等权限的用途与状态。",
    "content": "多家生活服务平台在设置页上线个人信息授权清单，用户可以集中查看定位、通讯录和相册等权限的用途与状态。平台表示，新页面会标注权限对应的具体功能，并提供关闭入口；用户在关闭前仍需确认是否会影响导航、扫码或图片上传等常用能力。隐私研究人员建议，除了查看系统权限，也应定期清理不再使用的第三方账号授权。",
    "url": "https://news.example.local/privacy-permission-list",
    "published": "2026-07-01T09:15:00+08:00",
    "source": "数字生活观察"
  },
  {
    "title": "公共图书馆增加周末夜间开放场次",
    "summary": "部分城市公共图书馆将在暑期增加周末夜间开放场次，并延长自习区和少儿阅读区服务时间。",
    "content": "部分城市公共图书馆将在暑期增加周末夜间开放场次，并延长自习区和少儿阅读区服务时间。馆方提醒，热门场馆可能继续采用预约入馆，夜间开放区域和借还服务时间也不完全相同。对普通读者来说，出发前最值得确认的是预约名额、闭馆时间、公共交通末班车以及少儿活动是否需要单独报名。",
    "url": "https://news.example.local/library-night-hours",
    "published": "2026-07-01T09:30:00+08:00",
    "source": "公共文化周报"
  }
]
